xcaptcha/__init__.py
xcaptcha/image.py
x_captcha-0.4.200808.dist-info/LICENSE
x_captcha-0.4.200808.dist-info/METADATA
x_captcha-0.4.200808.dist-info/WHEEL
x_captcha-0.4.200808.dist-info/top_level.txt
x_captcha-0.4.200808.dist-info/RECORD
