Metadata-Version: 2.1
Name: x-captcha
Version: 0.4.200808
Summary: A simple and powerful captcha generation library.
Home-page: https://www.github.com/eraare/x-captcha
Author: Leo
Author-email: r00kie@126.com
License: BSD
Keywords: captcha
Platform: UNKNOWN
Requires-Dist: Pillow
